gotji/__init__.py
gotji/gotji.py
gotji-1.0.9.dist-info/LICENSE
gotji-1.0.9.dist-info/METADATA
gotji-1.0.9.dist-info/WHEEL
gotji-1.0.9.dist-info/top_level.txt
gotji-1.0.9.dist-info/RECORD
