Metadata-Version: 2.1
Name: gotji
Version: 1.0.9
Summary: Dev by Meoaw
Home-page: https://github.com/exaDev99/gotji
Author: exaDev99
Author-email: meoawdev.me@gmail.com
License: MIT
Classifier: Programming Language :: Python :: 3
Classifier: Development Status :: 4 - Beta
Classifier: License :: OSI Approved :: MIT License
Classifier: Operating System :: OS Independent
License-File: LICENSE
Requires-Dist: requests
Requires-Dist: pystyle
Requires-Dist: replit
Requires-Dist: flask
Requires-Dist: flask-restful
